bugcatcher/__init__.py
bugcatcher/ci.py
bugcatcher-ci/__init__.py
bugcatcher-ci/ci.py
bugcatcher_ci-0.1.9.dist-info/LICENSE.txt
bugcatcher_ci-0.1.9.dist-info/METADATA
bugcatcher_ci-0.1.9.dist-info/WHEEL
bugcatcher_ci-0.1.9.dist-info/top_level.txt
bugcatcher_ci-0.1.9.dist-info/RECORD
