Metadata-Version: 2.1
Name: bugcatcher-ci
Version: 0.1.9
Summary: A continuous integration tool for Python static analysis
Home-page: https://github.com/faster-than-light/bugcatcher-ci
Author: Faster Than Light
Author-email: devops@fasterthanlight.dev
License: UNKNOWN
Project-URL: Bug Reports, https://github.com/faster-than-light/bugcatcher-ci/issues
Project-URL: Source, https://github.com/faster-than-light/bugcatcher-ci/
Keywords: CI CircleCI Travis-CI Python static analysis
Platform: UNKNOWN
Classifier: Development Status :: 3 - Alpha
Classifier: Intended Audience :: Developers
Classifier: Topic :: Software Development :: Build Tools
Classifier: License :: OSI Approved :: GNU General Public License v2 (GPLv2)
Classifier: Programming Language :: Python :: 3.5
Classifier: Programming Language :: Python :: 3.6
Classifier: Programming Language :: Python :: 3.7
Classifier: Programming Language :: Python :: 3.8
Requires-Python: >=3.5
Requires-Dist: bugcatcher (>=0.1.6)
Provides-Extra: dev
Requires-Dist: check-manifest ; extra == 'dev'
Provides-Extra: test
Requires-Dist: coverage ; extra == 'test'
